.DS_Store
PydTfinder/__init__.py
PydTfinder/PydTfinder.py
PydTfinder/__main__.py
PydTfinder-1.1.9.dist-info/RECORD
PydTfinder-1.1.9.dist-info/metadata.json
PydTfinder-1.1.9.dist-info/WHEEL
PydTfinder-1.1.9.dist-info/entry_points.txt
PydTfinder-1.1.9.dist-info/DESCRIPTION.rst
PydTfinder-1.1.9.dist-info/top_level.txt
PydTfinder-1.1.9.dist-info/METADATA
