Metadata-Version: 2.0
Name: PydTfinder
Version: 1.1.9
Summary: ::A tool to find the phase eq temperature at a given pressure with a given ΔT value::
Home-page: https://pypi.org/project/PydTfinder/
Author: wjgoarxiv
Author-email: woo_go@yahoo.com
License: MIT
Requires-Python: >=3.7
Requires-Dist: matplotlib
Requires-Dist: numpy
Requires-Dist: scikit-learn
Requires-Dist: scipy
Requires-Dist: pandas
Requires-Dist: seaborn
Requires-Dist: argparse
Requires-Dist: pyfiglet
Requires-Dist: tabulate
